Metadata-Version: 1.1
Name: listkraken
Version: 0.1.0
Summary: Kraken Python package
Home-page: https://github.com/boopathyganesh/kraken
Author: Kraken Rogers
Author-email: kraken@gmail.com
License: Apache Software License
Platform: UNKNOWN
Classifier: Development Status :: 1 - Planning
Classifier: Intended Audience :: Science/Research
Classifier: License :: OSI Approved :: Apache Software License
Classifier: Operating System :: POSIX :: Linux
Classifier: Programming Language :: Python :: 2
Classifier: Programming Language :: Python :: 2.7
Classifier: Programming Language :: Python :: 3
Classifier: Programming Language :: Python :: 3.4
Classifier: Programming Language :: Python :: 3.8
Classifier: Programming Language :: Python :: 3.10
